{
  "_fv": 28,
  "_type": "item",
  "definition": {
    "renderType": 0,
    "texture": "brownitem",
    "customModelName": "Normal",
    "name": "Brown",
    "rarity": "RARE",
    "creativeTab": {
      "value": "CUSTOM:Chaostab"
    },
    "stackSize": 64,
    "enchantability": 0,
    "useDuration": 32,
    "toolType": 1.0,
    "damageCount": 0,
    "recipeRemainder": {
      "value": ""
    },
    "destroyAnyBlock": false,
    "immuneToFire": true,
    "stayInGridWhenCrafting": false,
    "damageOnCrafting": false,
    "enableMeleeDamage": false,
    "damageVsEntity": 0.0,
    "specialInfo": [
      "It... multiplies?"
    ],
    "hasGlow": false,
    "guiBoundTo": "<NONE>",
    "inventorySize": 9,
    "inventoryStackSize": 64,
    "onItemInInventoryTick": {
      "name": "BrownItemInInventoryTick"
    },
    "hasDispenseBehavior": false,
    "isFood": true,
    "nutritionalValue": 0,
    "saturation": 0.0,
    "eatResultItem": {
      "value": ""
    },
    "isMeat": true,
    "isAlwaysEdible": true,
    "animation": "eat"
  }
}