{
  "_fv": 28,
  "_type": "structure",
  "definition": {
    "structure": "rick_roll_stairs",
    "randomlyRotateStructure": true,
    "surfaceDetectionType": "First motion blocking block",
    "spawnProbability": 7000,
    "minCountPerChunk": 1,
    "maxCountPerChunk": 1,
    "spawnLocation": "Ground",
    "spawnHeightOffset": 0,
    "spawnXOffset": 0,
    "spawnZOffset": 0,
    "spawnWorldTypes": [
      "Surface",
      "Nether",
      "End",
      "CUSTOM:Peemension",
      "CUSTOM:WoodDimension",
      "CUSTOM:Sus",
      "CUSTOM:Brazil",
      "CUSTOM:Cyberspace",
      "CUSTOM:Cioao",
      "CUSTOM:Aether"
    ],
    "restrictionBlocks": [],
    "restrictionBiomes": [],
    "ignoreBlocks": "STRUCTURE_BLOCK"
  }
}