{
  "name": "purechaos:backrooms_backrooms",
  "fallback": "minecraft:empty",
  "elements": [
    {
      "weight": 1,
      "element": {
        "element_type": "minecraft:single_pool_element",
        "location": "purechaos:b1_blank_space",
        "projection": "rigid",
        "processors": {
          "processors": []
        }
      }
    },
    {
      "weight": 1,
      "element": {
        "element_type": "minecraft:single_pool_element",
        "location": "purechaos:b1_c_bottom_space",
        "projection": "rigid",
        "processors": {
          "processors": []
        }
      }
    },
    {
      "weight": 1,
      "element": {
        "element_type": "minecraft:single_pool_element",
        "location": "purechaos:b1_c_left_space",
        "projection": "rigid",
        "processors": {
          "processors": []
        }
      }
    },
    {
      "weight": 1,
      "element": {
        "element_type": "minecraft:single_pool_element",
        "location": "purechaos:b1_c_right_space",
        "projection": "rigid",
        "processors": {
          "processors": []
        }
      }
    },
    {
      "weight": 1,
      "element": {
        "element_type": "minecraft:single_pool_element",
        "location": "purechaos:b1_c_top_space",
        "projection": "rigid",
        "processors": {
          "processors": []
        }
      }
    },
    {
      "weight": 1,
      "element": {
        "element_type": "minecraft:single_pool_element",
        "location": "purechaos:b1_t_bottom_space",
        "projection": "rigid",
        "processors": {
          "processors": []
        }
      }
    },
    {
      "weight": 1,
      "element": {
        "element_type": "minecraft:single_pool_element",
        "location": "purechaos:b1_t_left_space",
        "projection": "rigid",
        "processors": {
          "processors": []
        }
      }
    },
    {
      "weight": 1,
      "element": {
        "element_type": "minecraft:single_pool_element",
        "location": "purechaos:b1_t_right_space",
        "projection": "rigid",
        "processors": {
          "processors": []
        }
      }
    },
    {
      "weight": 1,
      "element": {
        "element_type": "minecraft:single_pool_element",
        "location": "purechaos:b1_t_top_space",
        "projection": "rigid",
        "processors": {
          "processors": []
        }
      }
    }
  ]
}